{
  "tasks": [
    {
      "id": 1,
      "text": "Food shopping",
      "day": "Feb 7th at 6:00AM",
      "reminder": false
    },
    {
      "id": 2,
      "text": "Food shopping",
      "day": "Feb 7th at 6:00AM",
      "reminder": false
    },
    {
      "id": 3,
      "text": "Food shopping",
      "day": "Feb 7th at 6:00AM",
      "reminder": true
    },
    {
      "id": 4,
      "text": "Food shopping",
      "day": "Feb 7th at 6:00AM",
      "reminder": true
    },
    {
      "text": "frg",
      "day": "fgfg",
      "reminder": true,
      "id": 5
    }
  ]
}